balanced_splits/__init__.py
balanced_splits/split.py
balanced_splits/tests/__init__.py
balanced_splits/tests/test_split.py
balanced_splits-0.2.0.dist-info/LICENSE
balanced_splits-0.2.0.dist-info/METADATA
balanced_splits-0.2.0.dist-info/WHEEL
balanced_splits-0.2.0.dist-info/top_level.txt
balanced_splits-0.2.0.dist-info/RECORD
