Metadata-Version: 2.1
Name: balanced-splits
Version: 0.2.0
Summary: Balanced splitting utility
Home-page: https://github.com/andersource/balanced-splits
Author: andersource
Author-email: hi@andersource.dev
License: UNKNOWN
Platform: UNKNOWN
Classifier: Programming Language :: Python :: 3
Classifier: License :: OSI Approved :: BSD License
Classifier: Operating System :: OS Independent
Requires-Python: >=3.6
Requires-Dist: numpy
Requires-Dist: scipy
Requires-Dist: pandas
